hhdm_apiclient_wrapper/__init__.py
hhdm_apiclient_wrapper/authentication_manager.py
hhdm_apiclient_wrapper/base_api_client.py
hhdm_apiclient_wrapper/generated/api_client.py
hhdm_apiclient_wrapper/models/__init__.py
hhdm_apiclient_wrapper/models/api_attachment_models.py
hhdm_apiclient_wrapper/models/api_models.py
hhdm_apiclient_wrapper/models/authentication_models.py
hhdm_apiclient_wrapper/models/mileage_models.py
hhdm_apiclient_wrapper/oauth_authentication_manager.py
hhdm_apiclient_wrapper-25.1.7.2.dist-info/LICENSE
hhdm_apiclient_wrapper-25.1.7.2.dist-info/METADATA
hhdm_apiclient_wrapper-25.1.7.2.dist-info/WHEEL
hhdm_apiclient_wrapper-25.1.7.2.dist-info/RECORD
