Metadata-Version: 2.1
Name: hhdm-apiclient-wrapper
Version: 25.1.7.2
Summary: Library that abstracts use of the HH Data Management API
Author: HH Development
Author-email: support@hh-dev.com
Requires-Python: >=3.10,<4.0
Classifier: Programming Language :: Python :: 3
Classifier: Programming Language :: Python :: 3.10
Classifier: Programming Language :: Python :: 3.11
Requires-Dist: httpx (>=0.28.1,<0.29.0)
Requires-Dist: lz4 (>=4.3.2,<5.0.0)
Requires-Dist: validators (>=0.34.0,<0.35.0)
